homogeneous_transform/__init__.py
homogeneous_transform/main.py
tests/__init__.py
tests/test_main.py
homogeneous_transform-0.1.1.dist-info/LICENSE
homogeneous_transform-0.1.1.dist-info/METADATA
homogeneous_transform-0.1.1.dist-info/WHEEL
homogeneous_transform-0.1.1.dist-info/top_level.txt
homogeneous_transform-0.1.1.dist-info/RECORD
