Metadata-Version: 2.2
Name: homogeneous-transform
Version: 0.1.1
Summary: Homogeneous transformation toolbox
Home-page: https://github.com/guimauve007/homogeneous-transform
Author: Gérémy Sauvageau
Author-email: geremysauvageau@gmail.com
Classifier: Programming Language :: Python :: 3
Classifier: License :: OSI Approved :: GNU General Public License v3 (GPLv3)
Classifier: Operating System :: OS Independent
Requires-Python: >=3.6
License-File: LICENSE
Requires-Dist: numpy
Requires-Dist: scipy
Dynamic: author
Dynamic: author-email
Dynamic: classifier
Dynamic: description
Dynamic: description-content-type
Dynamic: home-page
Dynamic: requires-dist
Dynamic: requires-python
Dynamic: summary
